{
"meta":{"test_sets":[],"test_metrics":[],"learn_metrics":[{"best_value":"Min","name":"RMSE"}],"launch_mode":"Train","parameters":"","iteration_count":100,"learn_sets":["learn"],"name":"experiment"},
"iterations":[
{"learn":[14.005006],"iteration":0,"passed_time":0.00126402693,"remaining_time":0.1251386661},
{"learn":[13.14441192],"iteration":1,"passed_time":0.002242533485,"remaining_time":0.1098841408},
{"learn":[12.34258257],"iteration":2,"passed_time":0.00332724418,"remaining_time":0.1075808951},
{"learn":[11.64527793],"iteration":3,"passed_time":0.004161690961,"remaining_time":0.09988058306},
{"learn":[11.02766183],"iteration":4,"passed_time":0.005034153655,"remaining_time":0.09564891945},
{"learn":[10.43485794],"iteration":5,"passed_time":0.00600243782,"remaining_time":0.09403819251},
{"learn":[9.890641275],"iteration":6,"passed_time":0.006874189281,"remaining_time":0.09132851474},
{"learn":[9.492161212],"iteration":7,"passed_time":0.007859326666,"remaining_time":0.09038225666},
{"learn":[9.105082953],"iteration":8,"passed_time":0.008853491036,"remaining_time":0.08951863159},
{"learn":[8.674157135],"iteration":9,"passed_time":0.009882354902,"remaining_time":0.08894119412},
{"learn":[8.341743544],"iteration":10,"passed_time":0.01076384325,"remaining_time":0.08708927717},
{"learn":[8.049372916],"iteration":11,"passed_time":0.01171911886,"remaining_time":0.08594020494},
{"learn":[7.757318612],"iteration":12,"passed_time":0.01279912205,"remaining_time":0.08565566298},
{"learn":[7.522206899],"iteration":13,"passed_time":0.01384699788,"remaining_time":0.08506012986},
{"learn":[7.297756655],"iteration":14,"passed_time":0.01482889031,"remaining_time":0.08403037842},
{"learn":[7.088359431],"iteration":15,"passed_time":0.01575190064,"remaining_time":0.08269747838},
{"learn":[6.882113791],"iteration":16,"passed_time":0.01658784001,"remaining_time":0.08098768948},
{"learn":[6.704728832],"iteration":17,"passed_time":0.01744346351,"remaining_time":0.07946466711},
{"learn":[6.563881962],"iteration":18,"passed_time":0.01828821883,"remaining_time":0.0779655645},
{"learn":[6.418790279],"iteration":19,"passed_time":0.01913385502,"remaining_time":0.07653542006},
{"learn":[6.315756953],"iteration":20,"passed_time":0.01994746567,"remaining_time":0.07504046609},
{"learn":[6.210157751],"iteration":21,"passed_time":0.02081159391,"remaining_time":0.07378656024},
{"learn":[6.115058449],"iteration":22,"passed_time":0.02174557327,"remaining_time":0.07280039746},
{"learn":[6.014819884],"iteration":23,"passed_time":0.02262814349,"remaining_time":0.07165578771},
{"learn":[5.93117229],"iteration":24,"passed_time":0.02363733792,"remaining_time":0.07091201375},
{"learn":[5.844857622],"iteration":25,"passed_time":0.02456651394,"remaining_time":0.06992007814},
{"learn":[5.771145213],"iteration":26,"passed_time":0.02536491823,"remaining_time":0.06857922336},
{"learn":[5.704018229],"iteration":27,"passed_time":0.02641935143,"remaining_time":0.0679354751},
{"learn":[5.665806474],"iteration":28,"passed_time":0.0274537352,"remaining_time":0.06721431721},
{"learn":[5.616500369],"iteration":29,"passed_time":0.02840233523,"remaining_time":0.06627211555},
{"learn":[5.558023666],"iteration":30,"passed_time":0.02935398957,"remaining_time":0.06533629936},
{"learn":[5.510080976],"iteration":31,"passed_time":0.0302972607,"remaining_time":0.06438167898},
{"learn":[5.468747792],"iteration":32,"passed_time":0.03124958619,"remaining_time":0.06344612954},
{"learn":[5.429275534],"iteration":33,"passed_time":0.03220435158,"remaining_time":0.06251432955},
{"learn":[5.402117324],"iteration":34,"passed_time":0.03309056813,"remaining_time":0.06145391223},
{"learn":[5.367635151],"iteration":35,"passed_time":0.03397361918,"remaining_time":0.06039754521},
{"learn":[5.345181232],"iteration":36,"passed_time":0.03477741281,"remaining_time":0.05921559479},
{"learn":[5.319151269],"iteration":37,"passed_time":0.03565527487,"remaining_time":0.05817439584},
{"learn":[5.296134146],"iteration":38,"passed_time":0.03658077953,"remaining_time":0.05721609106},
{"learn":[5.269629003],"iteration":39,"passed_time":0.03747910707,"remaining_time":0.0562186606},
{"learn":[5.251147059],"iteration":40,"passed_time":0.03839043248,"remaining_time":0.05524476868},
{"learn":[5.248003302],"iteration":41,"passed_time":0.03875445362,"remaining_time":0.053518055},
{"learn":[5.232376509],"iteration":42,"passed_time":0.03964585849,"remaining_time":0.05255381242},
{"learn":[5.213524255],"iteration":43,"passed_time":0.04045705496,"remaining_time":0.05149079722},
{"learn":[5.189691584],"iteration":44,"passed_time":0.0414241671,"remaining_time":0.05062953756},
{"learn":[5.166052198],"iteration":45,"passed_time":0.04243021674,"remaining_time":0.04980938487},
{"learn":[5.140406659],"iteration":46,"passed_time":0.04334769749,"remaining_time":0.0488814461},
{"learn":[5.118929684],"iteration":47,"passed_time":0.04422983696,"remaining_time":0.0479156567},
{"learn":[5.108792602],"iteration":48,"passed_time":0.04502574692,"remaining_time":0.04686353251},
{"learn":[5.098141225],"iteration":49,"passed_time":0.0458789362,"remaining_time":0.0458789362},
{"learn":[5.085926393],"iteration":50,"passed_time":0.0467293707,"remaining_time":0.04489684636},
{"learn":[5.067816804],"iteration":51,"passed_time":0.04759744579,"remaining_time":0.04393610381},
{"learn":[5.049834901],"iteration":52,"passed_time":0.04842389871,"remaining_time":0.04294194791},
{"learn":[5.03838627],"iteration":53,"passed_time":0.04930615305,"remaining_time":0.04200153778},
{"learn":[5.033534248],"iteration":54,"passed_time":0.05003827709,"remaining_time":0.04094040853},
{"learn":[5.023726885],"iteration":55,"passed_time":0.0509539901,"remaining_time":0.04003527794},
{"learn":[5.01290392],"iteration":56,"passed_time":0.05191251201,"remaining_time":0.03916207046},
{"learn":[5.005569127],"iteration":57,"passed_time":0.05274008153,"remaining_time":0.03819109352},
{"learn":[4.989969032],"iteration":58,"passed_time":0.05358523221,"remaining_time":0.03723719526},
{"learn":[4.976762446],"iteration":59,"passed_time":0.05449107745,"remaining_time":0.03632738496},
{"learn":[4.967222715],"iteration":60,"passed_time":0.05540539805,"remaining_time":0.03542312334},
{"learn":[4.954407599],"iteration":61,"passed_time":0.05628470261,"remaining_time":0.03449707579},
{"learn":[4.942125056],"iteration":62,"passed_time":0.05714501423,"remaining_time":0.03356135756},
{"learn":[4.930230716],"iteration":63,"passed_time":0.05810681649,"remaining_time":0.03268508428},
{"learn":[4.921695642],"iteration":64,"passed_time":0.05906540384,"remaining_time":0.03180444822},
{"learn":[4.906405625],"iteration":65,"passed_time":0.05993516719,"remaining_time":0.03087569219},
{"learn":[4.894330248],"iteration":66,"passed_time":0.06083942501,"remaining_time":0.02996568695},
{"learn":[4.88211557],"iteration":67,"passed_time":0.0617074046,"remaining_time":0.02903877864},
{"learn":[4.877946398],"iteration":68,"passed_time":0.06267511243,"remaining_time":0.02815838385},
{"learn":[4.863182126],"iteration":69,"passed_time":0.0637256796,"remaining_time":0.02731100554},
{"learn":[4.84646533],"iteration":70,"passed_time":0.06484337682,"remaining_time":0.02648532292},
{"learn":[4.838014752],"iteration":71,"passed_time":0.06581750077,"remaining_time":0.02559569474},
{"learn":[4.82981137],"iteration":72,"passed_time":0.06685641206,"remaining_time":0.02472771405},
{"learn":[4.817094767],"iteration":73,"passed_time":0.0678530003,"remaining_time":0.02384024335},
{"learn":[4.808314151],"iteration":74,"passed_time":0.06891519729,"remaining_time":0.02297173243},
{"learn":[4.796235023],"iteration":75,"passed_time":0.0699407601,"remaining_time":0.02208655582},
{"learn":[4.784434534],"iteration":76,"passed_time":0.07108847002,"remaining_time":0.02123421832},
{"learn":[4.774402487],"iteration":77,"passed_time":0.07196758392,"remaining_time":0.02029854931},
{"learn":[4.76731896],"iteration":78,"passed_time":0.07288678765,"remaining_time":0.01937496887},
{"learn":[4.75934113],"iteration":79,"passed_time":0.07382163351,"remaining_time":0.01845540838},
{"learn":[4.754106378],"iteration":80,"passed_time":0.07475059917,"remaining_time":0.01753409116},
{"learn":[4.744002932],"iteration":81,"passed_time":0.07569658968,"remaining_time":0.01661632456},
{"learn":[4.731700554],"iteration":82,"passed_time":0.07665350847,"remaining_time":0.01570011619},
{"learn":[4.723284153],"iteration":83,"passed_time":0.07750858101,"remaining_time":0.01476353924},
{"learn":[4.712232782],"iteration":84,"passed_time":0.07858195706,"remaining_time":0.01386740419},
{"learn":[4.703046867],"iteration":85,"passed_time":0.08000532025,"remaining_time":0.0130241219},
{"learn":[4.698601855],"iteration":86,"passed_time":0.08103464959,"remaining_time":0.0121086258},
{"learn":[4.692429407],"iteration":87,"passed_time":0.08190747291,"remaining_time":0.01116920085},
{"learn":[4.675027364],"iteration":88,"passed_time":0.08274883167,"remaining_time":0.01022738369},
{"learn":[4.662368584],"iteration":89,"passed_time":0.0835756953,"remaining_time":0.009286188367},
{"learn":[4.646206172],"iteration":90,"passed_time":0.08435386451,"remaining_time":0.008342689897},
{"learn":[4.641245848],"iteration":91,"passed_time":0.08524333202,"remaining_time":0.007412463654},
{"learn":[4.633900435],"iteration":92,"passed_time":0.08603170893,"remaining_time":0.006475504973},
{"learn":[4.624738236],"iteration":93,"passed_time":0.08677264357,"remaining_time":0.005538679377},
{"learn":[4.612798287],"iteration":94,"passed_time":0.08760581815,"remaining_time":0.004610832534},
{"learn":[4.605222001],"iteration":95,"passed_time":0.08841925851,"remaining_time":0.003684135771},
{"learn":[4.601725912],"iteration":96,"passed_time":0.0891819609,"remaining_time":0.002758204976},
{"learn":[4.59722371],"iteration":97,"passed_time":0.09019511219,"remaining_time":0.001840716575},
{"learn":[4.580235665],"iteration":98,"passed_time":0.09115026325,"remaining_time":0.0009207097298},
{"learn":[4.57591791],"iteration":99,"passed_time":0.09207524701,"remaining_time":0}
]}